[
    {
        "group": "乃木坂46",
        "member": "鈴木絢音",
        "type": "SHOWROOM個人配信",
        "airdate": "2020.10.31",
        "stream": [
            "19:30:17",
            "20:13:52"
        ],
        "mori_tw_gift": [
            {
                "user": 32770
            },
            3,
            74100
        ]
    },
    {
        "group": "乃木坂46",
        "member": "鈴木絢音",
        "type": "のぎおび",
        "airdate": "2020.10.30",
        "stream": [
            "18:30:18",
            "19:00:21"
        ],
        "mori_tw_gift": [
            {
                "user": 26335
            },
            3,
            45088
        ]
    },
    {
        "group": "日向坂46",
        "member": "佐々木美玲",
        "type": "SHOWROOM",
        "airdate": "2020.10.30",
        "stream": [
            "17:02:05",
            "18:01:09"
        ],
        "mori_tw_gift": [
            {
                "user": 48221
            },
            11,
            203600
        ]
    },
    {
        "group": "乃木坂46",
        "member": "吉田綾乃クリスティー",
        "type": "SHOWROOM個人配信",
        "airdate": "2020.10.29",
        "stream": [
            "20:07:10",
            "21:11:19"
        ],
        "mori_tw_gift": [
            {
                "user": 25731
            },
            5,
            132400
        ]
    },
    {
        "group": "日向坂46",
        "member": "富田鈴花",
        "type": "SHOWROOM",
        "airdate": "2020.10.29",
        "stream": [
            "20:00:08",
            "21:00:10"
        ],
        "mori_tw_gift": [
            {
                "user": 56370
            },
            8,
            194838
        ]
    },
    {
        "group": "乃木坂46",
        "member": "松尾美佑",
        "type": "のぎおび",
        "airdate": "2020.10.29",
        "stream": [
            "18:30:03",
            "19:00:17"
        ],
        "mori_tw_gift": [
            {
                "user": 18732
            },
            1,
            16250
        ]
    },
    {
        "group": "乃木坂46",
        "member": [
            "オールナイトニッポン",
            "新内眞衣",
            "梅澤美波"
        ],
        "type": [
            "乃木坂46配信",
            "オールナイトニッポン"
        ],
        "airdate": "2020.10.29",
        "stream": [
            "00:54:32",
            "03:00:08"
        ],
        "mori_tw_gift": [
            {
                "user": 65605
            },
            false,
            false
        ],
        "title": "乃木坂46のオールナイトニッポン"
    },
    {
        "group": "乃木坂46",
        "member": [
            "オールナイトニッポン",
            "新内眞衣"
        ],
        "type": [
            "乃木坂46配信",
            "オールナイトニッポン"
        ],
        "airdate": "2020.10.29",
        "stream": [
            "00:30:26",
            "00:53:15"
        ],
        "mori_tw_gift": [
            {
                "user": 19605
            },
            0,
            250
        ],
        "title": "乃木坂46のオールナイトニッポン 超直前スペシャル！"
    },
    {
        "group": "乃木坂46",
        "member": "清宮レイ",
        "type": "のぎおび",
        "airdate": "2020.10.26",
        "stream": [
            "18:30:25",
            "19:00:05"
        ],
        "mori_tw_gift": [
            {
                "user": 26371
            },
            5,
            98800
        ]
    },
    {
        "group": "乃木坂46",
        "member": "田村真佑",
        "type": "のぎおび",
        "airdate": "2020.10.23",
        "stream": [
            "17:30:08",
            "17:59:40"
        ],
        "mori_tw_gift": [
            {
                "user": 25451
            },
            0,
            12600
        ]
    },
    {
        "group": "乃木坂46",
        "member": "久保史緒里",
        "type": "のぎおび",
        "airdate": "2020.10.22",
        "stream": [
            "13:30:07",
            "14:00:17"
        ],
        "mori_tw_gift": [
            {
                "user": 27993
            },
            0,
            23250
        ]
    },
    {
        "group": "乃木坂46",
        "member": [
            "オールナイトニッポン",
            "白石麻衣",
            "秋元真夏",
            "大園桃子",
            "松村沙友理"
        ],
        "type": [
            "乃木坂46配信",
            "オールナイトニッポン"
        ],
        "airdate": "2020.10.22",
        "stream": [
            "00:55:46",
            "03:00:21"
        ],
        "mori_tw_gift": [
            {
                "user": 103308
            },
            false,
            false
        ],
        "title": "乃木坂46白石麻衣のオールナイトニッポン"
    },
    {
        "group": "乃木坂46",
        "member": [
            "オールナイトニッポン",
            "白石麻衣"
        ],
        "type": [
            "乃木坂46配信",
            "オールナイトニッポン"
        ],
        "airdate": "2020.10.22",
        "stream": [
            "00:31:15",
            "00:54:12"
        ],
        "mori_tw_gift": [
            {
                "user": 26558
            },
            1,
            11900
        ],
        "title": "乃木坂46白石麻衣のオールナイトニッポン 超直前スペシャル！"
    },
    {
        "group": "乃木坂46",
        "member": [
            "田村真佑",
            "向井葉月"
        ],
        "type": "猫舌",
        "airdate": "2020.10.21",
        "stream": [
            "18:50:28",
            "21:03:28"
        ],
        "mori_tw_gift": [
            {
                "user": 49394
            },
            2,
            125350
        ],
        "title": "猫舌SHOWROOM『乃木坂46にゃんば〜1』"
    },
    {
        "group": "乃木坂46",
        "member": "星野みなみ",
        "type": "のぎおび",
        "airdate": "2020.10.21",
        "stream": [
            "15:00:20",
            "15:30:15"
        ],
        "mori_tw_gift": [
            {
                "user": 31009
            },
            16,
            335650
        ]
    },
    {
        "group": "乃木坂46",
        "member": "新内眞衣",
        "type": "のぎおび",
        "airdate": "2020.10.20",
        "stream": [
            "18:30:19",
            "18:59:58"
        ],
        "mori_tw_gift": [
            {
                "user": 25175
            },
            2,
            57750
        ]
    },
    {
        "group": "乃木坂46",
        "member": "寺田蘭世",
        "type": "のぎおび",
        "airdate": "2020.10.19",
        "stream": [
            "18:15:12",
            "18:45:01"
        ],
        "mori_tw_gift": [
            {
                "user": 23280
            },
            3,
            86100
        ]
    },
    {
        "group": "乃木坂46",
        "member": "柴田柚菜",
        "type": "のぎおび",
        "airdate": "2020.10.16",
        "stream": [
            "17:30:06",
            "18:00:18"
        ],
        "mori_tw_gift": [
            {
                "user": 20695
            },
            1,
            48200
        ]
    },
    {
        "group": "乃木坂46",
        "member": "矢久保美緒",
        "type": "のぎおび",
        "airdate": "2020.10.15",
        "stream": [
            "18:30:34",
            "19:00:47"
        ],
        "mori_tw_gift": [
            {
                "user": 19844
            },
            3,
            62800
        ]
    },
    {
        "group": "乃木坂46",
        "member": [
            "オールナイトニッポン",
            "新内眞衣",
            "星野みなみ"
        ],
        "type": [
            "乃木坂46配信",
            "オールナイトニッポン"
        ],
        "airdate": "2020.10.15",
        "stream": [
            "00:54:06",
            "03:00:49"
        ],
        "mori_tw_gift": [
            {
                "user": 54076
            },
            false,
            false
        ],
        "title": "乃木坂46のオールナイトニッポン"
    },
    {
        "group": "乃木坂46",
        "member": [
            "オールナイトニッポン",
            "新内眞衣"
        ],
        "type": [
            "乃木坂46配信",
            "オールナイトニッポン"
        ],
        "airdate": "2020.10.15",
        "stream": [
            "00:30:37",
            "00:53:04"
        ],
        "mori_tw_gift": [
            {
                "user": 13169
            },
            0,
            50
        ],
        "title": "乃木坂46のオールナイトニッポン 超直前スペシャル！"
    },
    {
        "group": "乃木坂46",
        "member": "向井葉月",
        "type": "のぎおび",
        "airdate": "2020.10.14",
        "stream": [
            "13:30:06",
            "14:04:39"
        ],
        "mori_tw_gift": [
            {
                "user": 13299
            },
            1,
            26800
        ]
    },
    {
        "group": "乃木坂46",
        "member": "掛橋沙耶香",
        "type": "のぎおび",
        "airdate": "2020.10.13",
        "stream": [
            "21:30:09",
            "21:59:33"
        ],
        "mori_tw_gift": [
            {
                "user": 34090
            },
            2,
            147350
        ]
    },
    {
        "group": "乃木坂46",
        "member": "中田花奈",
        "type": [
            "個人配信",
            "写真集",
            "発売記念"
        ],
        "airdate": "2020.10.13",
        "stream": [
            "19:50:18",
            "21:16:28"
        ],
        "mori_tw_gift": [
            {
                "user": 47468
            },
            6,
            367856
        ],
        "title": "乃木坂46 中田花奈 ファースト写真集発売記念スペシャル！"
    },
    {
        "group": "乃木坂46",
        "member": "岩本蓮加",
        "type": "のぎおび",
        "airdate": "2020.10.12",
        "stream": [
            "18:29:52",
            "19:00:22"
        ],
        "mori_tw_gift": [
            {
                "user": 33249
            },
            3,
            80950
        ]
    },
    {
        "group": "日向坂46",
        "member": [
            "齊藤京子",
            "佐々木久美",
            "丹生明里",
            "渡邉美穂"
        ],
        "type": "SHOWROOM",
        "airdate": "2020.10.10",
        "stream": [
            "15:50:09",
            "17:00:59"
        ],
        "mori_tw_gift": [
            {
                "user": 71994
            },
            11,
            188164
        ],
        "title": "日向坂46とふしぎな図書室 ひなたとあなたの1ページ"
    },
    {
        "group": "乃木坂46",
        "member": "中田花奈",
        "type": "のぎおび",
        "airdate": "2020.10.09",
        "stream": [
            "19:02:11",
            "19:32:04"
        ],
        "mori_tw_gift": [
            {
                "user": 25916
            },
            2,
            186500
        ]
    },
    {
        "group": "乃木坂46",
        "member": "和田まあや",
        "type": "のぎおび",
        "airdate": "2020.10.08",
        "stream": [
            "21:00:38",
            "21:30:10"
        ],
        "mori_tw_gift": [
            {
                "user": 19826
            },
            0,
            5850
        ]
    },
    {
        "group": "乃木坂46",
        "member": [
            "オールナイトニッポン",
            "新内眞衣",
            "北野日奈子"
        ],
        "type": [
            "乃木坂46配信",
            "オールナイトニッポン"
        ],
        "airdate": "2020.10.08",
        "stream": [
            "00:54:06",
            "03:00:59"
        ],
        "mori_tw_gift": [
            {
                "user": 48446
            },
            false,
            false
        ],
        "title": "乃木坂46のオールナイトニッポン"
    },
    {
        "group": "乃木坂46",
        "member": [
            "オールナイトニッポン",
            "新内眞衣"
        ],
        "type": [
            "乃木坂46配信",
            "オールナイトニッポン"
        ],
        "airdate": "2020.10.08",
        "stream": [
            "00:30:04",
            "00:53:19"
        ],
        "mori_tw_gift": [
            {
                "user": 11916
            },
            0,
            0
        ],
        "title": "乃木坂46のオールナイトニッポン 超直前スペシャル！"
    },
    {
        "group": "乃木坂46",
        "member": [
            "阪口珠美",
            "吉田綾乃クリスティー"
        ],
        "type": "猫舌",
        "airdate": "2020.10.07",
        "stream": [
            "18:45:06",
            "21:01:26"
        ],
        "mori_tw_gift": [
            {
                "user": 54451
            },
            14,
            504950
        ],
        "title": "猫舌SHOWROOM『乃木坂46にゃんば〜1』"
    },
    {
        "group": "乃木坂46",
        "member": "与田祐希",
        "type": "のぎおび",
        "airdate": "2020.10.07",
        "stream": [
            "18:36:44",
            "19:01:07"
        ],
        "mori_tw_gift": [
            {
                "user": 52299
            },
            18,
            259300
        ]
    },
    {
        "group": "乃木坂46",
        "member": "吉田綾乃クリスティー",
        "type": "のぎおび",
        "airdate": "2020.10.06",
        "stream": [
            "18:30:09",
            "19:00:13"
        ],
        "mori_tw_gift": [
            {
                "user": 15901
            },
            3,
            62900
        ]
    },
    {
        "group": "乃木坂46",
        "member": "伊藤純奈",
        "type": "のぎおび",
        "airdate": "2020.10.05",
        "stream": [
            "18:40:32",
            "19:10:04"
        ],
        "mori_tw_gift": [
            {
                "user": 24243
            },
            0,
            44800
        ]
    },
    {
        "group": "乃木坂46",
        "member": "伊藤理々杏",
        "type": "のぎおび",
        "airdate": "2020.10.02",
        "stream": [
            "18:00:34",
            "18:30:12"
        ],
        "mori_tw_gift": [
            {
                "user": 20912
            },
            0,
            14400
        ]
    },
    {
        "group": "乃木坂46",
        "member": "弓木奈於",
        "type": "のぎおび",
        "airdate": "2020.10.01",
        "stream": [
            "21:15:06",
            "21:44:48"
        ],
        "mori_tw_gift": [
            {
                "user": 20369
            },
            4,
            62000
        ]
    },
    {
        "group": "乃木坂46",
        "member": [
            "オールナイトニッポン",
            "新内眞衣",
            "中田花奈"
        ],
        "type": [
            "乃木坂46配信",
            "オールナイトニッポン"
        ],
        "airdate": "2020.10.01",
        "stream": [
            "00:54:16",
            "03:00:57"
        ],
        "mori_tw_gift": [
            {
                "user": 45803
            },
            false,
            false
        ],
        "title": "乃木坂46のオールナイトニッポン"
    },
    {
        "group": "乃木坂46",
        "member": [
            "オールナイトニッポン",
            "新内眞衣"
        ],
        "type": [
            "乃木坂46配信",
            "オールナイトニッポン"
        ],
        "airdate": "2020.10.01",
        "stream": [
            "00:30:56",
            "00:53:10"
        ],
        "mori_tw_gift": [
            {
                "user": 11917
            },
            0,
            2500
        ],
        "title": "乃木坂46のオールナイトニッポン 超直前スペシャル！"
    }
]