[
    {
        "group": "乃木坂46",
        "member": "渡辺みり愛",
        "type": [
            "個人配信",
            "写真集",
            "発売記念"
        ],
        "airdate": "2021.08.31",
        "stream": [
            "19:52:27",
            "20:55:29"
        ],
        "mori_tw_gift": [
            {
                "user": 36796
            },
            2,
            322830
        ],
        "title": "渡辺みり愛1st写真集「消極的な華やかさ」発売記念SP"
    },
    {
        "group": "乃木坂46",
        "member": "矢久保美緒",
        "type": "のぎおび",
        "airdate": "2021.08.31",
        "stream": [
            "19:00:05",
            "19:30:00"
        ],
        "mori_tw_gift": [
            {
                "user": 18905
            },
            4,
            76950
        ]
    },
    {
        "group": "乃木坂46",
        "member": "渡辺みり愛",
        "type": "SHOWROOM個人配信",
        "airdate": "2021.08.30",
        "stream": [
            "19:50:46",
            "20:50:01"
        ],
        "mori_tw_gift": [
            {
                "user": 29375
            },
            0,
            127600
        ]
    },
    {
        "group": "乃木坂46",
        "member": "弓木奈於",
        "type": "のぎおび",
        "airdate": "2021.08.30",
        "stream": [
            "19:00:26",
            "19:30:27"
        ],
        "mori_tw_gift": [
            {
                "user": 19928
            },
            1,
            37250
        ]
    },
    {
        "group": "日向坂46",
        "member": "森本茉莉",
        "type": "SHOWROOM",
        "airdate": "2021.08.28",
        "stream": [
            "18:02:05",
            "19:01:22"
        ],
        "mori_tw_gift": [
            {
                "user": 26392
            },
            9,
            186250
        ]
    },
    {
        "group": "乃木坂46",
        "member": "与田祐希",
        "type": "のぎおび",
        "airdate": "2021.08.27",
        "stream": [
            "19:15:54",
            "19:46:34"
        ],
        "mori_tw_gift": [
            {
                "user": 47349
            },
            13,
            521550
        ]
    },
    {
        "group": "乃木坂46",
        "member": "寺田蘭世",
        "type": "のぎおび",
        "airdate": "2021.08.26",
        "stream": [
            "19:00:02",
            "19:30:45"
        ],
        "mori_tw_gift": [
            {
                "user": 24570
            },
            5,
            236210
        ]
    },
    {
        "group": "乃木坂46",
        "member": [
            "岩本蓮加",
            "佐藤楓"
        ],
        "type": "猫舌 乃木坂46にゃんば〜1",
        "airdate": "2021.08.25",
        "stream": [
            "19:00:08",
            "20:00:11"
        ],
        "mori_tw_gift": [
            {
                "user": 32735
            },
            9,
            340600
        ],
        "title": "猫舌SHOWROOM『乃木坂46にゃんば〜1』"
    },
    {
        "group": "乃木坂46",
        "member": "賀喜遥香",
        "type": "のぎおび",
        "airdate": "2021.08.25",
        "stream": [
            "18:15:52",
            "18:46:04"
        ],
        "mori_tw_gift": [
            {
                "user": 42251
            },
            28,
            762300
        ]
    },
    {
        "group": "櫻坂46",
        "member": "齋藤冬優花",
        "type": "SHOWROOM",
        "airdate": "2021.08.25",
        "stream": [
            "17:31:10",
            "18:00:21"
        ],
        "mori_tw_gift": [
            {
                "user": 12827
            },
            3,
            113938
        ]
    },
    {
        "group": "乃木坂46",
        "member": "黒見明香",
        "type": "のぎおび",
        "airdate": "2021.08.24",
        "stream": [
            "18:15:20",
            "18:45:23"
        ],
        "mori_tw_gift": [
            {
                "user": 15481
            },
            1,
            64000
        ]
    },
    {
        "group": "乃木坂46",
        "member": [
            "掛橋沙耶香",
            "柴田柚菜",
            "早川聖来",
            "弓木奈於"
        ],
        "type": "SHOWROOM個人配信",
        "airdate": "2021.08.23",
        "stream": [
            "19:15:16",
            "19:45:53"
        ],
        "mori_tw_gift": [
            {
                "user": 29056
            },
            0,
            29350
        ],
        "title": "「乃木坂スター誕生！」特別配信ルーム"
    },
    {
        "group": "乃木坂46",
        "member": "伊藤理々杏",
        "type": "のぎおび",
        "airdate": "2021.08.23",
        "stream": [
            "18:30:16",
            "18:59:51"
        ],
        "mori_tw_gift": [
            {
                "user": 21353
            },
            1,
            53700
        ]
    },
    {
        "group": "櫻坂46",
        "member": "松田里奈",
        "type": "SHOWROOM",
        "airdate": "2021.08.22",
        "stream": [
            "19:00:29",
            "20:00:44"
        ],
        "mori_tw_gift": [
            {
                "user": 24013
            },
            2,
            227850
        ]
    },
    {
        "group": "櫻坂46",
        "member": "土生瑞穂",
        "type": "SHOWROOM",
        "airdate": "2021.08.20",
        "stream": [
            "18:45:51",
            "19:17:51"
        ],
        "mori_tw_gift": [
            {
                "user": 22260
            },
            5,
            255700
        ]
    },
    {
        "group": "乃木坂46",
        "member": "岩本蓮加",
        "type": "のぎおび",
        "airdate": "2021.08.19",
        "stream": [
            "18:30:12",
            "19:00:07"
        ],
        "mori_tw_gift": [
            {
                "user": 28261
            },
            2,
            142900
        ]
    },
    {
        "group": "乃木坂46",
        "member": "新内眞衣",
        "type": "のぎおび",
        "airdate": "2021.08.18",
        "stream": [
            "22:30:11",
            "23:04:08"
        ],
        "mori_tw_gift": [
            {
                "user": 36871
            },
            5,
            178350
        ]
    },
    {
        "group": "乃木坂46",
        "member": [
            "伊藤純奈",
            "渡辺みり愛"
        ],
        "type": "猫舌 乃木坂46にゃんば〜1",
        "airdate": "2021.08.18",
        "stream": [
            "18:45:12",
            "21:01:31"
        ],
        "mori_tw_gift": [
            {
                "user": 54148
            },
            6,
            382574
        ],
        "title": "猫舌SHOWROOM『乃木坂46にゃんば〜1』"
    },
    {
        "group": "櫻坂46",
        "member": "田村保乃",
        "type": [
            "個人配信",
            "写真集",
            "発売記念"
        ],
        "airdate": "2021.08.18",
        "stream": [
            "18:03:26",
            "19:00:14"
        ],
        "mori_tw_gift": [
            {
                "user": 34346
            },
            15,
            314714
        ],
        "title": "田村保乃1st写真集「一歩目」発売記念SP！"
    },
    {
        "group": "櫻坂46",
        "member": "田村保乃",
        "type": [
            "個人配信",
            "写真集",
            "発売記念"
        ],
        "airdate": "2021.08.17",
        "stream": [
            "19:57:47",
            "20:58:44"
        ],
        "mori_tw_gift": [
            {
                "user": 45057
            },
            9,
            421800
        ],
        "title": "田村保乃1st写真集「一歩目」発売記念SP！"
    },
    {
        "group": "乃木坂46",
        "member": "鈴木絢音",
        "type": "のぎおび",
        "airdate": "2021.08.17",
        "stream": [
            "18:00:06",
            "18:30:20"
        ],
        "mori_tw_gift": [
            {
                "user": 27329
            },
            3,
            177100
        ]
    },
    {
        "group": "乃木坂46",
        "member": "掛橋沙耶香",
        "type": "のぎおび",
        "airdate": "2021.08.16",
        "stream": [
            "19:00:00",
            "19:30:00"
        ],
        "mori_tw_gift": [
            {
                "user": 33383
            },
            7,
            397150
        ]
    },
    {
        "group": "日向坂46",
        "member": [
            "渡邉美穂",
            "富田鈴花"
        ],
        "type": "SHOWROOM",
        "airdate": "2021.08.15",
        "stream": [
            "20:00:31",
            "21:00:17"
        ],
        "mori_tw_gift": [
            {
                "user": 62655
            },
            3,
            511286
        ]
    },
    {
        "group": "日向坂46",
        "member": "山口陽世",
        "type": "SHOWROOM",
        "airdate": "2021.08.15",
        "stream": [
            "19:00:15",
            "19:59:46"
        ],
        "mori_tw_gift": [
            {
                "user": 41707
            },
            7,
            248400
        ]
    },
    {
        "group": "乃木坂46",
        "member": "阪口珠美",
        "type": "のぎおび",
        "airdate": "2021.08.13",
        "stream": [
            "18:30:31",
            "18:59:54"
        ],
        "mori_tw_gift": [
            {
                "user": 21682
            },
            2,
            75990
        ]
    },
    {
        "group": "乃木坂46",
        "member": "北川悠理",
        "type": "のぎおび",
        "airdate": "2021.08.12",
        "stream": [
            "20:00:04",
            "20:30:10"
        ],
        "mori_tw_gift": [
            {
                "user": 17427
            },
            0,
            72378
        ]
    },
    {
        "group": "乃木坂46",
        "member": "北野日奈子",
        "type": "のぎおび",
        "airdate": "2021.08.11",
        "stream": [
            "21:01:09",
            "21:30:59"
        ],
        "mori_tw_gift": [
            {
                "user": 31634
            },
            1,
            189876
        ]
    },
    {
        "group": "乃木坂46",
        "member": [
            "鈴木絢音",
            "寺田蘭世"
        ],
        "type": "猫舌 乃木坂46にゃんば〜1",
        "airdate": "2021.08.11",
        "stream": [
            "19:00:03",
            "19:59:51"
        ],
        "mori_tw_gift": [
            {
                "user": 32758
            },
            4,
            259150
        ],
        "title": "猫舌SHOWROOM『乃木坂46にゃんば〜1』"
    },
    {
        "group": "乃木坂46",
        "member": "筒井あやめ",
        "type": "のぎおび",
        "airdate": "2021.08.10",
        "stream": [
            "19:30:24",
            "20:00:05"
        ],
        "mori_tw_gift": [
            {
                "user": 32151
            },
            2,
            134100
        ]
    },
    {
        "group": "日向坂46",
        "member": "髙橋未来虹",
        "type": "SHOWROOM",
        "airdate": "2021.08.09",
        "stream": [
            "19:01:50",
            "20:01:07"
        ],
        "mori_tw_gift": [
            {
                "user": 31405
            },
            9,
            279450
        ]
    },
    {
        "group": "乃木坂46",
        "member": "渡辺みり愛",
        "type": "SHOWROOM個人配信",
        "airdate": "2021.08.07",
        "stream": [
            "18:55:11",
            "19:48:30"
        ],
        "mori_tw_gift": [
            {
                "user": 26650
            },
            4,
            110100
        ]
    },
    {
        "group": "乃木坂46",
        "member": "松尾美佑",
        "type": "のぎおび",
        "airdate": "2021.08.06",
        "stream": [
            "18:30:03",
            "19:00:02"
        ],
        "mori_tw_gift": [
            {
                "user": 15765
            },
            0,
            36850
        ]
    },
    {
        "group": "乃木坂46",
        "member": "中村麗乃",
        "type": "のぎおび",
        "airdate": "2021.08.05",
        "stream": [
            "19:55:26",
            "20:25:31"
        ],
        "mori_tw_gift": [
            {
                "user": 20538
            },
            3,
            75400
        ]
    },
    {
        "group": "乃木坂46",
        "member": [
            "清宮レイ",
            "柴田柚菜"
        ],
        "type": "猫舌 乃木坂46にゃんば〜1",
        "airdate": "2021.08.04",
        "stream": [
            "19:00:07",
            "19:59:47"
        ],
        "mori_tw_gift": [
            {
                "user": 28550
            },
            12,
            469000
        ],
        "title": "猫舌SHOWROOM『乃木坂46にゃんば〜1』"
    },
    {
        "group": "乃木坂46",
        "member": "田村真佑",
        "type": "のぎおび",
        "airdate": "2021.08.04",
        "stream": [
            "18:17:38",
            "18:46:28"
        ],
        "mori_tw_gift": [
            {
                "user": 26916
            },
            1,
            77700
        ]
    },
    {
        "group": "乃木坂46",
        "member": "山崎怜奈",
        "type": "のぎおび",
        "airdate": "2021.08.03",
        "stream": [
            "19:01:03",
            "19:32:43"
        ],
        "mori_tw_gift": [
            {
                "user": 20051
            },
            1,
            90150
        ]
    },
    {
        "group": "日向坂46",
        "member": "上村ひなの",
        "type": "SHOWROOM",
        "airdate": "2021.08.02",
        "stream": [
            "19:01:10",
            "20:00:36"
        ],
        "mori_tw_gift": [
            {
                "user": 43191
            },
            5,
            312600
        ]
    },
    {
        "group": "乃木坂46",
        "member": "佐藤璃果",
        "type": "のぎおび",
        "airdate": "2021.08.02",
        "stream": [
            "18:30:37",
            "19:00:16"
        ],
        "mori_tw_gift": [
            {
                "user": 18581
            },
            0,
            89600
        ]
    }
]