[
    {
        "group": "乃木坂46",
        "member": "林瑠奈",
        "type": "のぎおび",
        "airdate": "2021.10.29",
        "stream": [
            "20:02:02",
            "20:31:05"
        ],
        "mori_tw_gift": [
            {
                "user": 18436
            },
            2,
            41450
        ]
    },
    {
        "group": "乃木坂46",
        "member": [
            "オールナイトニッポン",
            "新内眞衣",
            "与田祐希"
        ],
        "type": [
            "乃木坂46配信",
            "オールナイトニッポン"
        ],
        "airdate": "2021.10.28",
        "stream": [
            "00:57:04",
            "03:01:13"
        ],
        "mori_tw_gift": [
            {
                "user": 47122
            },
            false,
            false
        ],
        "title": "乃木坂46のオールナイトニッポン"
    },
    {
        "group": "乃木坂46",
        "member": [
            "オールナイトニッポン",
            "新内眞衣"
        ],
        "type": [
            "乃木坂46配信",
            "オールナイトニッポン"
        ],
        "airdate": "2021.10.28",
        "stream": [
            "00:30:46",
            "00:54:31"
        ],
        "mori_tw_gift": [
            {
                "user": 11141
            },
            0,
            3000
        ],
        "title": "乃木坂46のオールナイトニッポン 超直前スペシャル！"
    },
    {
        "group": "乃木坂46",
        "member": "樋口日奈",
        "type": "のぎおび",
        "airdate": "2021.10.27",
        "stream": [
            "16:00:06",
            "16:30:19"
        ],
        "mori_tw_gift": [
            {
                "user": 16750
            },
            1,
            31950
        ]
    },
    {
        "group": "乃木坂46",
        "member": "遠藤さくら",
        "type": "のぎおび",
        "airdate": "2021.10.26",
        "stream": [
            "17:15:22",
            "17:45:53"
        ],
        "mori_tw_gift": [
            {
                "user": 34436
            },
            2,
            231150
        ]
    },
    {
        "group": "乃木坂46",
        "member": "和田まあや",
        "type": "のぎおび",
        "airdate": "2021.10.25",
        "stream": [
            "18:15:20",
            "18:45:21"
        ],
        "mori_tw_gift": [
            {
                "user": 13211
            },
            0,
            6700
        ]
    },
    {
        "group": "日向坂46",
        "member": [
            "影山優佳",
            "高瀬愛奈",
            "宮田愛萌",
            "山口陽世"
        ],
        "type": "SHOWROOM",
        "airdate": "2021.10.22",
        "stream": [
            "20:20:04",
            "21:33:15"
        ],
        "mori_tw_gift": [
            {
                "user": 43090
            },
            false,
            false
        ],
        "title": "UNI'S ON AIR 2周年記念SHOWROOM第二弾"
    },
    {
        "group": "乃木坂46",
        "member": "岩本蓮加",
        "type": "のぎおび",
        "airdate": "2021.10.22",
        "stream": [
            "18:30:29",
            "19:00:41"
        ],
        "mori_tw_gift": [
            {
                "user": 27847
            },
            0,
            67900
        ]
    },
    {
        "group": "乃木坂46",
        "member": "早川聖来",
        "type": "のぎおび",
        "airdate": "2021.10.21",
        "stream": [
            "19:00:14",
            "19:30:29"
        ],
        "mori_tw_gift": [
            {
                "user": 24545
            },
            2,
            61100
        ]
    },
    {
        "group": "乃木坂46",
        "member": [
            "オールナイトニッポン",
            "新内眞衣",
            "寺田蘭世"
        ],
        "type": [
            "乃木坂46配信",
            "オールナイトニッポン"
        ],
        "airdate": "2021.10.21",
        "stream": [
            "00:55:50",
            "03:00:44"
        ],
        "mori_tw_gift": [
            {
                "user": 39559
            },
            false,
            false
        ],
        "title": "乃木坂46のオールナイトニッポン"
    },
    {
        "group": "乃木坂46",
        "member": [
            "オールナイトニッポン",
            "新内眞衣"
        ],
        "type": [
            "乃木坂46配信",
            "オールナイトニッポン"
        ],
        "airdate": "2021.10.21",
        "stream": [
            "00:30:07",
            "00:55:00"
        ],
        "mori_tw_gift": [
            {
                "user": 10729
            },
            1,
            15500
        ],
        "title": "乃木坂46のオールナイトニッポン 超直前スペシャル！"
    },
    {
        "group": "乃木坂46",
        "member": [
            "遠藤さくら",
            "清宮レイ"
        ],
        "type": "猫舌 乃木坂46にゃんば〜1",
        "airdate": "2021.10.20",
        "stream": [
            "18:46:22",
            "21:00:53"
        ],
        "mori_tw_gift": [
            {
                "user": 57174
            },
            8,
            390900
        ],
        "title": "猫舌SHOWROOM『乃木坂46にゃんば〜1』"
    },
    {
        "group": "乃木坂46",
        "member": "鈴木絢音",
        "type": "のぎおび",
        "airdate": "2021.10.20",
        "stream": [
            "18:15:15",
            "18:45:03"
        ],
        "mori_tw_gift": [
            {
                "user": 22194
            },
            0,
            74400
        ]
    },
    {
        "group": "乃木坂46",
        "member": "与田祐希",
        "type": "のぎおび",
        "airdate": "2021.10.19",
        "stream": [
            "19:00:47",
            "19:31:54"
        ],
        "mori_tw_gift": [
            {
                "user": 40834
            },
            6,
            248150
        ]
    },
    {
        "group": "乃木坂46",
        "member": "賀喜遥香",
        "type": "のぎおび",
        "airdate": "2021.10.18",
        "stream": [
            "18:30:11",
            "19:00:20"
        ],
        "mori_tw_gift": [
            {
                "user": 36351
            },
            6,
            216850
        ]
    },
    {
        "group": "日向坂46",
        "member": [
            "潮紗理菜",
            "高本彩花",
            "上村ひなの"
        ],
        "type": "SHOWROOM",
        "airdate": "2021.10.17",
        "stream": [
            "18:50:23",
            "20:00:49"
        ],
        "mori_tw_gift": [
            {
                "user": 41181
            },
            5,
            156588
        ],
        "title": "日向坂46×KOEHARU LIVESHOW！開催決定SP"
    },
    {
        "group": "乃木坂46",
        "member": "清宮レイ",
        "type": "のぎおび",
        "airdate": "2021.10.15",
        "stream": [
            "18:30:09",
            "19:00:43"
        ],
        "mori_tw_gift": [
            {
                "user": 22469
            },
            1,
            76800
        ]
    },
    {
        "group": "乃木坂46",
        "member": "伊藤理々杏",
        "type": "のぎおび",
        "airdate": "2021.10.14",
        "stream": [
            "19:30:22",
            "20:00:07"
        ],
        "mori_tw_gift": [
            {
                "user": 18273
            },
            0,
            35714
        ]
    },
    {
        "group": "乃木坂46",
        "member": [
            "オールナイトニッポン",
            "新内眞衣",
            "弓木奈於"
        ],
        "type": [
            "乃木坂46配信",
            "オールナイトニッポン"
        ],
        "airdate": "2021.10.14",
        "stream": [
            "00:54:29",
            "03:01:01"
        ],
        "mori_tw_gift": [
            {
                "user": 42807
            },
            false,
            false
        ],
        "title": "乃木坂46のオールナイトニッポン"
    },
    {
        "group": "乃木坂46",
        "member": [
            "オールナイトニッポン",
            "新内眞衣"
        ],
        "type": [
            "乃木坂46配信",
            "オールナイトニッポン"
        ],
        "airdate": "2021.10.14",
        "stream": [
            "00:30:02",
            "00:53:42"
        ],
        "mori_tw_gift": [
            {
                "user": 10831
            },
            0,
            17600
        ],
        "title": "乃木坂46のオールナイトニッポン 超直前スペシャル！"
    },
    {
        "group": "乃木坂46",
        "member": "柴田柚菜",
        "type": "のぎおび",
        "airdate": "2021.10.13",
        "stream": [
            "21:00:42",
            "21:30:01"
        ],
        "mori_tw_gift": [
            {
                "user": 27338
            },
            1,
            62150
        ]
    },
    {
        "group": "乃木坂46",
        "member": [
            "阪口珠美",
            "吉田綾乃クリスティー"
        ],
        "type": "猫舌 乃木坂46にゃんば〜1",
        "airdate": "2021.10.13",
        "stream": [
            "18:46:09",
            "21:00:07"
        ],
        "mori_tw_gift": [
            {
                "user": 38630
            },
            6,
            308720
        ],
        "title": "猫舌SHOWROOM『乃木坂46にゃんば〜1』"
    },
    {
        "group": "乃木坂46",
        "member": "金川紗耶",
        "type": "のぎおび",
        "airdate": "2021.10.12",
        "stream": [
            "20:00:28",
            "20:31:31"
        ],
        "mori_tw_gift": [
            {
                "user": 21264
            },
            3,
            69200
        ]
    },
    {
        "group": "乃木坂46",
        "member": "松尾美佑",
        "type": "のぎおび",
        "airdate": "2021.10.11",
        "stream": [
            "19:55:27",
            "20:25:06"
        ],
        "mori_tw_gift": [
            {
                "user": 18266
            },
            0,
            39850
        ]
    },
    {
        "group": "乃木坂46",
        "member": "山下美月",
        "type": "のぎおび",
        "airdate": "2021.10.08",
        "stream": [
            "18:31:23",
            "19:02:04"
        ],
        "mori_tw_gift": [
            {
                "user": 43414
            },
            9,
            433100
        ]
    },
    {
        "group": "乃木坂46",
        "member": "黒見明香",
        "type": "のぎおび",
        "airdate": "2021.10.07",
        "stream": [
            "18:30:22",
            "19:00:04"
        ],
        "mori_tw_gift": [
            {
                "user": 12850
            },
            2,
            41500
        ]
    },
    {
        "group": "乃木坂46",
        "member": [
            "オールナイトニッポン",
            "新内眞衣",
            "秋元真夏"
        ],
        "type": [
            "乃木坂46配信",
            "オールナイトニッポン"
        ],
        "airdate": "2021.10.07",
        "stream": [
            "00:54:13",
            "03:01:05"
        ],
        "mori_tw_gift": [
            {
                "user": 48781
            },
            false,
            false
        ],
        "title": "乃木坂46のオールナイトニッポン"
    },
    {
        "group": "乃木坂46",
        "member": [
            "オールナイトニッポン",
            "新内眞衣"
        ],
        "type": [
            "乃木坂46配信",
            "オールナイトニッポン"
        ],
        "airdate": "2021.10.07",
        "stream": [
            "00:30:23",
            "00:52:53"
        ],
        "mori_tw_gift": [
            {
                "user": 14404
            },
            1,
            14300
        ],
        "title": "乃木坂46のオールナイトニッポン 超直前スペシャル！"
    },
    {
        "group": "乃木坂46",
        "member": [
            "矢久保美緒",
            "北川悠理"
        ],
        "type": "猫舌 乃木坂46にゃんば〜1",
        "airdate": "2021.10.06",
        "stream": [
            "18:45:01",
            "21:01:17"
        ],
        "mori_tw_gift": [
            {
                "user": 43798
            },
            10,
            394244
        ],
        "title": "猫舌SHOWROOM『乃木坂46にゃんば〜1』"
    },
    {
        "group": "乃木坂46",
        "member": "筒井あやめ",
        "type": "のぎおび",
        "airdate": "2021.10.06",
        "stream": [
            "18:15:10",
            "18:45:23"
        ],
        "mori_tw_gift": [
            {
                "user": 29140
            },
            1,
            73000
        ]
    },
    {
        "group": "乃木坂46",
        "member": "新内眞衣",
        "type": "のぎおび",
        "airdate": "2021.10.05",
        "stream": [
            "21:00:15",
            "21:32:15"
        ],
        "mori_tw_gift": [
            {
                "user": 26915
            },
            1,
            71200
        ]
    },
    {
        "group": "乃木坂46",
        "member": "弓木奈於",
        "type": "のぎおび",
        "airdate": "2021.10.04",
        "stream": [
            "19:30:13",
            "20:00:06"
        ],
        "mori_tw_gift": [
            {
                "user": 17441
            },
            0,
            22250
        ]
    },
    {
        "group": "乃木坂46",
        "member": "久保史緒里",
        "type": "のぎおび",
        "airdate": "2021.10.01",
        "stream": [
            "18:30:21",
            "19:00:09"
        ],
        "mori_tw_gift": [
            {
                "user": 29499
            },
            1,
            99600
        ]
    }
]