{
	"IMGSitemap": "https://ik.imagekit.io/moearchive/menu-button/newbanner_docrandom_mariko.png",
	"url": "life-of-mariko-in-kabukicho",
	"nameShowTitle": "Life of Mariko in Kabukicho (2023)",
	"descSynopsis": "Film hiburan unik ini mengisahkan Mariko, seorang pemilik bar sekaligus detektif, yang menerima permintaan dari FBI untuk mencari makhluk luar angkasa yang bersembunyi di Kabukicho. Dalam pencarian bersama kekasihnya, MASAYA, yang mengaku sebagai ninja, kisah mereka berhimpitan dengan nasib berbagai manusia kesepian di kota tersebut, mulai dari yakuza yang bangkrut hingga gadis kabaret yang gila host, hingga akhirnya bermuara pada rahasia yang dipendam Mariko sejak 15 tahun lalu.",
	"episodes": {
		"01": {
			"descEpsListName": "Movie",
			"descEpisode": "Movie",
			"descOnAirDate": "30 Juni 2023",
			"memberParticipate": "久保史緒里",
			"linkHardsub": "",
			"linkTrakteer": "https://trakteer.id/moefangsubs/showcase/life-of-mariko-in-kabukicho-ogsIs",
			"filePassword": "",
			"imageThumbEps": "https://ik.imagekit.io/moearchive/thumb/docrandom/mariko.jpg",
			"imageThumbBig": "https://ik.imagekit.io/mLsKqNSuB/post/random/mariko.jpg",
			"imageThumbA": "https://ik.imagekit.io/mLsKqNSuB/post/random/mariko1.jpg",
			"imageThumbB": "https://ik.imagekit.io/mLsKqNSuB/post/random/mariko2.jpg",
			"imageThumbC": "https://ik.imagekit.io/mLsKqNSuB/post/random/mariko3.jpg",
			"imageThumbD": "https://ik.imagekit.io/mLsKqNSuB/post/random/mariko4.jpg",
			"nameShow": "探偵マリコの生涯で一番悲惨な日"
		}
	}
}